postgresml_django/__init__.py
postgresml_django/main.py
postgresml_django-0.1.0.dist-info/METADATA
postgresml_django-0.1.0.dist-info/WHEEL
postgresml_django-0.1.0.dist-info/licenses/LICENSE
postgresml_django-0.1.0.dist-info/RECORD
