Metadata-Version: 2.3
Name: postgresml-django
Version: 0.1.0
Summary: PostgresML Django integration that enables automatic embedding of specified fields.
Project-URL: Homepage, https://postgresml.org
Project-URL: Repository, https://github.com/postgresml/postgresml-django
Project-URL: Documentation, https://github.com/postgresml/postgresml-django
Author-email: PostgresML <team@postgresml.org>
License-File: LICENSE
Keywords: django,embeddings,machine learning,vector databases
Classifier: License :: OSI Approved :: MIT License
Classifier: Operating System :: OS Independent
Classifier: Programming Language :: Python :: 3
Requires-Python: >=3.8
Requires-Dist: django
Requires-Dist: pgvector
